django_pandas/__init__.py
django_pandas/io.py
django_pandas/managers.py
django_pandas/models.py
django_pandas/utils.py
django_pandas/tests/__init__.py
django_pandas/tests/models.py
django_pandas/tests/test_io.py
django_pandas/tests/test_manager.py
django_pandas/tests/tests.py
django_pandas-0.6.7.dist-info/AUTHORS.rst
django_pandas-0.6.7.dist-info/LICENSE.rst
django_pandas-0.6.7.dist-info/METADATA
django_pandas-0.6.7.dist-info/WHEEL
django_pandas-0.6.7.dist-info/top_level.txt
django_pandas-0.6.7.dist-info/RECORD
