Metadata-Version: 2.1
Name: django-pandas
Version: 0.6.7
Summary: Tools for working with pydata.pandas in your Django projects
Home-page: https://github.com/chrisdev/django-pandas/
Author: Christopher Clarke
Author-email: cclarke@chrisdev.com
Classifier: Development Status :: 3 - Alpha
Classifier: Environment :: Web Environment
Classifier: Intended Audience :: Developers
Classifier: License :: OSI Approved :: BSD License
Classifier: Operating System :: OS Independent
Classifier: Programming Language :: Python
Classifier: Programming Language :: Python :: 2.7
Classifier: Programming Language :: Python :: 3.3
Classifier: Programming Language :: Python :: 3.4
Classifier: Programming Language :: Python :: 3.6
Classifier: Programming Language :: Python :: 3.7
Classifier: Programming Language :: Python :: 3.8
Classifier: Programming Language :: Python :: 3.9
Classifier: Programming Language :: Python :: 3.10
Classifier: Framework :: Django
License-File: LICENSE.rst
License-File: AUTHORS.rst
Requires-Dist: pandas>=0.14.1
Requires-Dist: six>=1.15.0
Provides-Extra: test
Requires-Dist: pandas>=0.20.1; extra == "test"
Requires-Dist: coverage==5.4; extra == "test"
Requires-Dist: semver==2.10.1; extra == "test"
